{
    "version": "6.0.0",
    "summary": "echarts-webcomponent option types",
    "repository": "https://github.com/kkpoon/elm-echarts.git",
    "license": "Apache-2.0",
    "source-directories": [
        "src",
        "example"
    ],
    "exposed-modules": [
        "ECharts",
        "ECharts.PieChart",
        "ECharts.Style"
    ],
    "dependencies": {
        "elm-lang/core": "5.1.1 <= v < 6.0.0",
        "elm-lang/html": "2.0.0 <= v < 3.0.0"
    },
    "elm-version": "0.18.0 <= v < 0.19.0"
}
